Metadata-Version: 2.1
Name: dariap-cine
Version: 1.0.5
Summary: Proyecto UF4
Home-page: UNKNOWN
Author: daria
Author-email: y1159554_t@iespoblenou.org
License: UNKNOWN
Platform: UNKNOWN
Classifier: Programming Language :: Python :: 3
Classifier: License :: OSI Approved :: MIT License
Classifier: Operating System :: OS Independent
